adapt.py
denoise.py
biodenoising/__init__.py
biodenoising/adapt.py
biodenoising/htdemucs.py
biodenoising/hubconf.py
biodenoising/selection_table.py
biodenoising/conf/config.yaml
biodenoising/conf/config_adapt.yaml
biodenoising/datasets/NoiseCleanRndSet.py
biodenoising/datasets/__init__.py
biodenoising/datasets/dataprune.py
biodenoising/datasets/gng.py
biodenoising/denoiser/__init__.py
biodenoising/denoiser/audio.py
biodenoising/denoiser/augment.py
biodenoising/denoiser/cleanunet.py
biodenoising/denoiser/data.py
biodenoising/denoiser/demucs.py
biodenoising/denoiser/denoise.py
biodenoising/denoiser/distrib.py
biodenoising/denoiser/dsp.py
biodenoising/denoiser/enhance.py
biodenoising/denoiser/evaluate.py
biodenoising/denoiser/evaluate_speech.py
biodenoising/denoiser/executor.py
biodenoising/denoiser/hdemucs.py
biodenoising/denoiser/htdemucs.py
biodenoising/denoiser/live.py
biodenoising/denoiser/loss.py
biodenoising/denoiser/noise.py
biodenoising/denoiser/pretrained.py
biodenoising/denoiser/resample.py
biodenoising/denoiser/solver.py
biodenoising/denoiser/spec.py
biodenoising/denoiser/states.py
biodenoising/denoiser/stft_loss.py
biodenoising/denoiser/transformer.py
biodenoising/denoiser/utils.py
biodenoising-0.3.3.dist-info/licenses/LICENSE
biodenoising-0.3.3.dist-info/METADATA
biodenoising-0.3.3.dist-info/WHEEL
biodenoising-0.3.3.dist-info/entry_points.txt
biodenoising-0.3.3.dist-info/top_level.txt
biodenoising-0.3.3.dist-info/RECORD
