Metadata-Version: 2.4
Name: biodenoising
Version: 0.3.3
Summary: Animal vocalization denoising
Home-page: https://github.com/earthspecies/biodenoising
Author: Marius Miron
Author-email: Marius Miron <info@mariusmiron.com>
License: MIT License
Project-URL: Homepage, https://github.com/earthspecies/biodenoising
Project-URL: Issues, https://github.com/earthspecies/biodenoising/issues
Classifier: Topic :: Multimedia :: Sound/Audio :: Analysis
Classifier: Topic :: Scientific/Engineering :: Artificial Intelligence
Classifier: Intended Audience :: Information Technology
Classifier: Intended Audience :: Science/Research
Classifier: Intended Audience :: System Administrators
Classifier: Intended Audience :: Telecommunications Industry
Classifier: Programming Language :: Python :: 3
Classifier: Programming Language :: Python :: 3 :: Only
Classifier: Programming Language :: Python :: 3.8
Classifier: Programming Language :: Python :: 3.9
Classifier: Programming Language :: Python :: 3.10
Classifier: Programming Language :: Python :: 3.11
Classifier: Programming Language :: Python :: 3.12
Requires-Python: >=3.8.0
License-File: LICENSE
Requires-Dist: julius
Requires-Dist: librosa
Requires-Dist: norbert
Requires-Dist: numpy>=1.19
Requires-Dist: six
Requires-Dist: sounddevice>=0.4
Requires-Dist: torch>=1.5
Requires-Dist: torchaudio>=0.5
Requires-Dist: openunmix
Requires-Dist: asteroid
Requires-Dist: einops
Requires-Dist: omegaconf==1.4.1
Requires-Dist: noisereduce
Requires-Dist: scikit-fuzzy
Requires-Dist: prosemble
Dynamic: author
Dynamic: home-page
Dynamic: license-file
Dynamic: requires-python
